gabiteodoru_qpython-2.0.0.data/data/CHANGELOG.txt
gabiteodoru_qpython-2.0.0.data/data/LICENSE
gabiteodoru_qpython-2.0.0.data/data/README.rst
gabiteodoru_qpython-2.0.0.data/data/requirements.txt
gabiteodoru_qpython-2.0.0.dist-info/licenses/LICENSE
qpython/__init__.py
qpython/_pandas.py
qpython/fastutils.pyx
qpython/qcollection.py
qpython/qconnection.py
qpython/qreader.py
qpython/qtemporal.py
qpython/qtype.py
qpython/qwriter.py
qpython/utils.py
gabiteodoru_qpython-2.0.0.dist-info/METADATA
gabiteodoru_qpython-2.0.0.dist-info/WHEEL
gabiteodoru_qpython-2.0.0.dist-info/top_level.txt
gabiteodoru_qpython-2.0.0.dist-info/RECORD
